wrds_tools/__init__.py
wrds_tools/wrds_connection.py
wrds_tools-0.0.13.dist-info/LICENSE
wrds_tools-0.0.13.dist-info/METADATA
wrds_tools-0.0.13.dist-info/WHEEL
wrds_tools-0.0.13.dist-info/top_level.txt
wrds_tools-0.0.13.dist-info/RECORD
