Metadata-Version: 2.1
Name: wrds-tools
Version: 0.0.13
Summary: Various tools to create a connection to the WRDS service and download commonly used data.
Home-page: UNKNOWN
Author: Julian Barg
Author-email: barg.julian@gmail.com
License: UNKNOWN
Platform: UNKNOWN
Requires-Dist: pandas
Requires-Dist: wrds
